{
  "date": "2026-06-06",
  "scrapedAt": "2026-06-06T19:40:42.032Z",
  "games": {
    "castle-fireworks": {
      "name": "Castle Fireworks Remixed",
      "today": {
        "topAvatar": "b54494163cd9812a5b5d4332f0a39280.png",
        "scores": [
          {
            "rank": 1,
            "username": "JustForFun",
            "score": 9816
          },
          {
            "rank": 2,
            "username": "MissAnnaNovang",
            "score": 7045
          }
        ]
      },
      "yesterday": {
        "topAvatar": "b54494163cd9812a5b5d4332f0a39280.png",
        "scores": [
          {
            "rank": 1,
            "username": "JustForFun",
            "score": 9796
          },
          {
            "rank": 2,
            "username": "MollyMolusk",
            "score": 8471
          },
          {
            "rank": 3,
            "username": "MissAnnaNovang",
            "score": 7780
          },
          {
            "rank": 4,
            "username": "King",
            "score": 6498
          },
          {
            "rank": 5,
            "username": "PrincessCutezada",
            "score": 4397
          },
          {
            "rank": 6,
            "username": "RoseBonbon",
            "score": 625
          },
          {
            "rank": 7,
            "username": "FrankensteinsBride",
            "score": 392
          },
          {
            "rank": 8,
            "username": "NewNinjaCat",
            "score": 40
          },
          {
            "rank": 9,
            "username": "BigFoxMol",
            "score": 0
          }
        ]
      },
      "highscores": {
        "topAvatar": "3cecfa3c5f95e9d87354a9596d9b0a34.png",
        "scores": [
          {
            "rank": 1,
            "username": "kazino",
            "score": 11430
          },
          {
            "rank": 2,
            "username": "Nayru",
            "score": 11363
          },
          {
            "rank": 3,
            "username": "BRlTT",
            "score": 11335
          },
          {
            "rank": 4,
            "username": "Pepa",
            "score": 10937
          },
          {
            "rank": 5,
            "username": "Acemaradona",
            "score": 10714
          },
          {
            "rank": 6,
            "username": "MacRose",
            "score": 10507
          },
          {
            "rank": 7,
            "username": "Jewelsy",
            "score": 10500
          },
          {
            "rank": 8,
            "username": "VMKNeec",
            "score": 10465
          },
          {
            "rank": 9,
            "username": "JustForFun",
            "score": 9974
          },
          {
            "rank": 10,
            "username": "onigiri",
            "score": 9926
          }
        ]
      }
    },
    "pirates": {
      "name": "Pirates of the Caribbean",
      "today": {
        "topAvatar": "5e7d4a38987dfd493b3c9438fed33075.png",
        "scores": [
          {
            "rank": 1,
            "username": "tizzi",
            "score": 335
          },
          {
            "rank": 2,
            "username": "airham",
            "score": 306
          },
          {
            "rank": 3,
            "username": "Ang",
            "score": 235
          },
          {
            "rank": 4,
            "username": "Detox",
            "score": 214
          },
          {
            "rank": 5,
            "username": "BrightEyes",
            "score": 210
          },
          {
            "rank": 6,
            "username": "Lazarus",
            "score": 189
          },
          {
            "rank": 7,
            "username": "GypsyRose",
            "score": 174
          },
          {
            "rank": 8,
            "username": "Diamond-K",
            "score": 169
          },
          {
            "rank": 9,
            "username": "happycatyomyno",
            "score": 167
          },
          {
            "rank": 10,
            "username": "Diamond-J",
            "score": 135
          }
        ]
      },
      "yesterday": {
        "topAvatar": "5e7d4a38987dfd493b3c9438fed33075.png",
        "scores": [
          {
            "rank": 1,
            "username": "tizzi",
            "score": 327
          },
          {
            "rank": 2,
            "username": "GypsyRose",
            "score": 316
          },
          {
            "rank": 3,
            "username": "Erie",
            "score": 298
          },
          {
            "rank": 4,
            "username": "magickate",
            "score": 270
          },
          {
            "rank": 5,
            "username": "Detox",
            "score": 268
          },
          {
            "rank": 6,
            "username": "CristianoRonaldo",
            "score": 244
          },
          {
            "rank": 7,
            "username": "LoveCervere",
            "score": 241
          },
          {
            "rank": 8,
            "username": "Myth",
            "score": 238
          },
          {
            "rank": 9,
            "username": "Diamond-J",
            "score": 229
          },
          {
            "rank": 10,
            "username": "Cool_Beanss",
            "score": 218
          }
        ]
      },
      "highscores": {
        "topAvatar": "5c674a3438c1dd5d77bf52f8cb6cf8f4.png",
        "scores": [
          {
            "rank": 1,
            "username": "scortatia",
            "score": 707
          },
          {
            "rank": 2,
            "username": "airham",
            "score": 678
          },
          {
            "rank": 3,
            "username": "magickate",
            "score": 440
          },
          {
            "rank": 4,
            "username": "Luckymaxer",
            "score": 420
          },
          {
            "rank": 5,
            "username": "Arkadia",
            "score": 413
          },
          {
            "rank": 6,
            "username": "Erie",
            "score": 401
          },
          {
            "rank": 7,
            "username": "Katana",
            "score": 399
          },
          {
            "rank": 8,
            "username": "tizzi",
            "score": 397
          },
          {
            "rank": 9,
            "username": "Myth",
            "score": 396
          },
          {
            "rank": 10,
            "username": "kazino",
            "score": 390
          }
        ]
      }
    },
    "haunted-mansion": {
      "name": "Haunted Mansion",
      "today": {
        "topAvatar": "373a6e780622eaa9ef773ad9ef542364.png",
        "scores": [
          {
            "rank": 1,
            "username": "Blueclay",
            "score": 128
          },
          {
            "rank": 2,
            "username": "MissyKinz",
            "score": 111
          },
          {
            "rank": 3,
            "username": "PrincessCutezada",
            "score": 95
          },
          {
            "rank": 4,
            "username": "RockStar_Olivia",
            "score": 93
          },
          {
            "rank": 5,
            "username": "Wdwdreamer",
            "score": 85
          },
          {
            "rank": 6,
            "username": "AliceJane",
            "score": 79
          },
          {
            "rank": 7,
            "username": "Bernardo_S_Rocks",
            "score": 68
          },
          {
            "rank": 8,
            "username": "JustForFun",
            "score": 66
          },
          {
            "rank": 9,
            "username": "EVOL",
            "score": 61
          },
          {
            "rank": 10,
            "username": "PrincessFunGirl",
            "score": 59
          }
        ]
      },
      "yesterday": {
        "topAvatar": "373a6e780622eaa9ef773ad9ef542364.png",
        "scores": [
          {
            "rank": 1,
            "username": "Blueclay",
            "score": 137
          },
          {
            "rank": 2,
            "username": "Rstar",
            "score": 133
          },
          {
            "rank": 3,
            "username": "EVOL",
            "score": 126
          },
          {
            "rank": 4,
            "username": "goatduck",
            "score": 124
          },
          {
            "rank": 5,
            "username": "waterfallglow",
            "score": 124
          },
          {
            "rank": 6,
            "username": "Izabelle",
            "score": 123
          },
          {
            "rank": 7,
            "username": "MissyKinz",
            "score": 122
          },
          {
            "rank": 8,
            "username": "Mikki",
            "score": 121
          },
          {
            "rank": 9,
            "username": "scortatia",
            "score": 119
          },
          {
            "rank": 10,
            "username": "Glaze",
            "score": 118
          }
        ]
      },
      "highscores": {
        "topAvatar": "c5dcefd3ac6f61eea430b4ef039f87f9.png",
        "scores": [
          {
            "rank": 1,
            "username": "AstroVioletRose",
            "score": 162
          },
          {
            "rank": 2,
            "username": "scortatia",
            "score": 156
          },
          {
            "rank": 3,
            "username": "Blueclay",
            "score": 155
          },
          {
            "rank": 4,
            "username": "EVOL",
            "score": 153
          },
          {
            "rank": 5,
            "username": "-Misty-",
            "score": 150
          },
          {
            "rank": 6,
            "username": "JustForFun",
            "score": 147
          },
          {
            "rank": 7,
            "username": "PrinceGeminii",
            "score": 146
          },
          {
            "rank": 8,
            "username": "dizlindsey",
            "score": 146
          },
          {
            "rank": 9,
            "username": "MissyKinz",
            "score": 145
          },
          {
            "rank": 10,
            "username": "Sandblasted_OctoNuggie",
            "score": 144
          }
        ]
      }
    },
    "jungle-cruise": {
      "name": "Jungle Cruise",
      "today": {
        "topAvatar": "5c674a3438c1dd5d77bf52f8cb6cf8f4.png",
        "scores": [
          {
            "rank": 1,
            "username": "scortatia",
            "score": 53794
          },
          {
            "rank": 2,
            "username": "Izabelle",
            "score": 50412
          },
          {
            "rank": 3,
            "username": "BlueSorcerer",
            "score": 48950
          },
          {
            "rank": 4,
            "username": "JellyFishFriend",
            "score": 44453
          },
          {
            "rank": 5,
            "username": "JennyKaye",
            "score": 42903
          },
          {
            "rank": 6,
            "username": "MissAnnaNovang",
            "score": 40754
          },
          {
            "rank": 7,
            "username": "Princessmagic",
            "score": 39695
          },
          {
            "rank": 8,
            "username": "starmagic",
            "score": 37625
          },
          {
            "rank": 9,
            "username": "Guest10150617",
            "score": 29717
          },
          {
            "rank": 10,
            "username": "Guest10150621",
            "score": 7127
          }
        ]
      },
      "yesterday": {
        "topAvatar": "044e085f79227d104cc586360c0d2ae6.png",
        "scores": [
          {
            "rank": 1,
            "username": "DesKismet",
            "score": 55691
          },
          {
            "rank": 2,
            "username": "Rstar",
            "score": 55219
          },
          {
            "rank": 3,
            "username": "BlueSorcerer",
            "score": 48850
          },
          {
            "rank": 4,
            "username": "JustForFun",
            "score": 47469
          },
          {
            "rank": 5,
            "username": "BigFoxMol",
            "score": 47275
          },
          {
            "rank": 6,
            "username": "JellyFishFriend",
            "score": 44741
          },
          {
            "rank": 7,
            "username": "BravaCentauri",
            "score": 44552
          },
          {
            "rank": 8,
            "username": "MissAnnaNovang",
            "score": 40520
          },
          {
            "rank": 9,
            "username": "starmagic",
            "score": 40284
          },
          {
            "rank": 10,
            "username": "mickeygirl55",
            "score": 39668
          }
        ]
      },
      "highscores": {
        "topAvatar": "5e7a45acc4d11bc61167dc1510ad1064.png",
        "scores": [
          {
            "rank": 1,
            "username": "Nayru",
            "score": 58721
          },
          {
            "rank": 2,
            "username": "DesKismet",
            "score": 56216
          },
          {
            "rank": 3,
            "username": "MadCrazyTurtle",
            "score": 55943
          },
          {
            "rank": 4,
            "username": "scortatia",
            "score": 55644
          },
          {
            "rank": 5,
            "username": "MagicalPixieDust",
            "score": 55565
          },
          {
            "rank": 6,
            "username": "BRlTT",
            "score": 55496
          },
          {
            "rank": 7,
            "username": "Rstar",
            "score": 55219
          },
          {
            "rank": 8,
            "username": "Focus",
            "score": 55144
          },
          {
            "rank": 9,
            "username": "TropicalShyFire",
            "score": 55103
          },
          {
            "rank": 10,
            "username": "airham",
            "score": 54886
          }
        ]
      }
    }
  }
}