{
  "date": "2026-04-11",
  "scrapedAt": "2026-04-11T18:56:11.353Z",
  "games": {
    "castle-fireworks": {
      "name": "Castle Fireworks Remixed",
      "today": {
        "topAvatar": "5fb8f1623dcdd699f2d69ff3e3249cad.png",
        "scores": [
          {
            "rank": 1,
            "username": "JustForFun",
            "score": 9036
          },
          {
            "rank": 2,
            "username": "MissAnnaNovang",
            "score": 8024
          },
          {
            "rank": 3,
            "username": "PrincessCutezada",
            "score": 4731
          },
          {
            "rank": 4,
            "username": "DustOnYourCeiling",
            "score": 3173
          },
          {
            "rank": 5,
            "username": "Guest10150075",
            "score": 389
          }
        ]
      },
      "yesterday": {
        "topAvatar": "11db56f207312fd63fdc1859d6e0c2c7.png",
        "scores": [
          {
            "rank": 1,
            "username": "kazino",
            "score": 11372
          },
          {
            "rank": 2,
            "username": "Nayru",
            "score": 10820
          },
          {
            "rank": 3,
            "username": "Jewelsy",
            "score": 9846
          },
          {
            "rank": 4,
            "username": "JustForFun",
            "score": 9771
          },
          {
            "rank": 5,
            "username": "MollyMolusk",
            "score": 8503
          },
          {
            "rank": 6,
            "username": "MissAnnaNovang",
            "score": 7902
          },
          {
            "rank": 7,
            "username": "mandie_baby",
            "score": 4572
          },
          {
            "rank": 8,
            "username": "PrincessCutezada",
            "score": 4229
          },
          {
            "rank": 9,
            "username": "Jorb",
            "score": 3852
          },
          {
            "rank": 10,
            "username": "Prilla",
            "score": 3161
          }
        ]
      },
      "highscores": {
        "topAvatar": "11db56f207312fd63fdc1859d6e0c2c7.png",
        "scores": [
          {
            "rank": 1,
            "username": "kazino",
            "score": 11372
          },
          {
            "rank": 2,
            "username": "Nayru",
            "score": 11363
          },
          {
            "rank": 3,
            "username": "BRlTT",
            "score": 11312
          },
          {
            "rank": 4,
            "username": "Pepa",
            "score": 10937
          },
          {
            "rank": 5,
            "username": "Jewelsy",
            "score": 10500
          },
          {
            "rank": 6,
            "username": "JustForFun",
            "score": 9829
          },
          {
            "rank": 7,
            "username": "bellemeansbeauty",
            "score": 9245
          },
          {
            "rank": 8,
            "username": "scortatia",
            "score": 8792
          },
          {
            "rank": 9,
            "username": "MollyMolusk",
            "score": 8566
          },
          {
            "rank": 10,
            "username": "GypsyRose",
            "score": 8464
          }
        ]
      }
    },
    "pirates": {
      "name": "Pirates of the Caribbean",
      "today": {
        "topAvatar": "4847a7c95156e51c036d6a47d1eea0fc.png",
        "scores": [
          {
            "rank": 1,
            "username": "tizzi",
            "score": 378
          },
          {
            "rank": 2,
            "username": "magickate",
            "score": 347
          },
          {
            "rank": 3,
            "username": "scortatia",
            "score": 298
          },
          {
            "rank": 4,
            "username": "angelofyourdreams",
            "score": 272
          },
          {
            "rank": 5,
            "username": "kazino",
            "score": 261
          },
          {
            "rank": 6,
            "username": "airham",
            "score": 254
          },
          {
            "rank": 7,
            "username": "Luckymaxer",
            "score": 252
          },
          {
            "rank": 8,
            "username": "mandie_baby",
            "score": 241
          },
          {
            "rank": 9,
            "username": "Erie",
            "score": 232
          },
          {
            "rank": 10,
            "username": "CristianoRonaldo",
            "score": 226
          }
        ]
      },
      "yesterday": {
        "topAvatar": "e21e75831ac3f66d5d8e88be0010295a.png",
        "scores": [
          {
            "rank": 1,
            "username": "MagicalPixieDust",
            "score": 343
          },
          {
            "rank": 2,
            "username": "tizzi",
            "score": 324
          },
          {
            "rank": 3,
            "username": "sapphire",
            "score": 315
          },
          {
            "rank": 4,
            "username": "magickate",
            "score": 308
          },
          {
            "rank": 5,
            "username": "mandie_baby",
            "score": 308
          },
          {
            "rank": 6,
            "username": "eeriee",
            "score": 291
          },
          {
            "rank": 7,
            "username": "Erie",
            "score": 273
          },
          {
            "rank": 8,
            "username": "angelofyourdreams",
            "score": 261
          },
          {
            "rank": 9,
            "username": "EpicRose",
            "score": 250
          },
          {
            "rank": 10,
            "username": "charliethehamsterr",
            "score": 243
          }
        ]
      },
      "highscores": {
        "topAvatar": "8d34f0aadc6b9ef42d59df9690e420ff.png",
        "scores": [
          {
            "rank": 1,
            "username": "Luckymaxer",
            "score": 420
          },
          {
            "rank": 2,
            "username": "Myth",
            "score": 396
          },
          {
            "rank": 3,
            "username": "kazino",
            "score": 390
          },
          {
            "rank": 4,
            "username": "magickate",
            "score": 385
          },
          {
            "rank": 5,
            "username": "angelofyourdreams",
            "score": 381
          },
          {
            "rank": 6,
            "username": "Lavenous",
            "score": 381
          },
          {
            "rank": 7,
            "username": "Satellite",
            "score": 378
          },
          {
            "rank": 8,
            "username": "tizzi",
            "score": 378
          },
          {
            "rank": 9,
            "username": "CristianoRonaldo",
            "score": 351
          },
          {
            "rank": 10,
            "username": "mandie_baby",
            "score": 349
          }
        ]
      }
    },
    "haunted-mansion": {
      "name": "Haunted Mansion",
      "today": {
        "topAvatar": "c88518d8be917bad75425a18dbacbabd.png",
        "scores": [
          {
            "rank": 1,
            "username": "dizlindsey",
            "score": 144
          },
          {
            "rank": 2,
            "username": "EVOL",
            "score": 135
          },
          {
            "rank": 3,
            "username": "airham",
            "score": 118
          },
          {
            "rank": 4,
            "username": "MissyKinz",
            "score": 115
          },
          {
            "rank": 5,
            "username": "Izabelle",
            "score": 115
          },
          {
            "rank": 6,
            "username": "CashisKing",
            "score": 112
          },
          {
            "rank": 7,
            "username": "Shadow_Rose",
            "score": 74
          },
          {
            "rank": 8,
            "username": "Sandblasted_OctoNuggie",
            "score": 71
          },
          {
            "rank": 9,
            "username": "charliethehamsterr",
            "score": 66
          },
          {
            "rank": 10,
            "username": "scortatia",
            "score": 60
          }
        ]
      },
      "yesterday": {
        "topAvatar": "98907fa488bfb7204dd6e60696edfb49.png",
        "scores": [
          {
            "rank": 1,
            "username": "scortatia",
            "score": 135
          },
          {
            "rank": 2,
            "username": "Whitney",
            "score": 130
          },
          {
            "rank": 3,
            "username": "dizlindsey",
            "score": 127
          },
          {
            "rank": 4,
            "username": "Glaze",
            "score": 121
          },
          {
            "rank": 5,
            "username": "AmandaJeanne",
            "score": 117
          },
          {
            "rank": 6,
            "username": "Izabelle",
            "score": 114
          },
          {
            "rank": 7,
            "username": "Niki2",
            "score": 113
          },
          {
            "rank": 8,
            "username": "MissyKinz",
            "score": 113
          },
          {
            "rank": 9,
            "username": "EVOL",
            "score": 110
          },
          {
            "rank": 10,
            "username": "PrincessCutezada",
            "score": 109
          }
        ]
      },
      "highscores": {
        "topAvatar": "5e52e521f87670e15b2aa2972ebf8729.png",
        "scores": [
          {
            "rank": 1,
            "username": "AstroVioletRose",
            "score": 159
          },
          {
            "rank": 2,
            "username": "Blueclay",
            "score": 155
          },
          {
            "rank": 3,
            "username": "EVOL",
            "score": 153
          },
          {
            "rank": 4,
            "username": "MissyKinz",
            "score": 145
          },
          {
            "rank": 5,
            "username": "Niki2",
            "score": 144
          },
          {
            "rank": 6,
            "username": "dizlindsey",
            "score": 144
          },
          {
            "rank": 7,
            "username": "Sandblasted_OctoNuggie",
            "score": 143
          },
          {
            "rank": 8,
            "username": "ArrowToTheHeart",
            "score": 140
          },
          {
            "rank": 9,
            "username": "Kroberts2018",
            "score": 139
          },
          {
            "rank": 10,
            "username": "-Misty-",
            "score": 139
          }
        ]
      }
    },
    "jungle-cruise": {
      "name": "Jungle Cruise",
      "today": {
        "topAvatar": "5fb8f1623dcdd699f2d69ff3e3249cad.png",
        "scores": [
          {
            "rank": 1,
            "username": "JustForFun",
            "score": 50175
          },
          {
            "rank": 2,
            "username": "DustOnYourCeiling",
            "score": 40737
          },
          {
            "rank": 3,
            "username": "PrincessCutezada",
            "score": 40496
          },
          {
            "rank": 4,
            "username": "mandie_baby",
            "score": 37858
          },
          {
            "rank": 5,
            "username": "BravaCentauri",
            "score": 35470
          }
        ]
      },
      "yesterday": {
        "topAvatar": "61d4519aaa58e392d421df79cdae35d0.png",
        "scores": [
          {
            "rank": 1,
            "username": "Nayru",
            "score": 57680
          },
          {
            "rank": 2,
            "username": "Horseytink",
            "score": 53580
          },
          {
            "rank": 3,
            "username": "aldisneyfans",
            "score": 52427
          },
          {
            "rank": 4,
            "username": "HappyToughFish",
            "score": 51702
          },
          {
            "rank": 5,
            "username": "BlueSorcerer",
            "score": 46487
          },
          {
            "rank": 6,
            "username": "Prilla",
            "score": 42839
          },
          {
            "rank": 7,
            "username": "PrincessCutezada",
            "score": 38434
          },
          {
            "rank": 8,
            "username": "DollahBrillz",
            "score": 38287
          },
          {
            "rank": 9,
            "username": "tweetier",
            "score": 37446
          },
          {
            "rank": 10,
            "username": "Jlew",
            "score": 21260
          }
        ]
      },
      "highscores": {
        "topAvatar": "61d4519aaa58e392d421df79cdae35d0.png",
        "scores": [
          {
            "rank": 1,
            "username": "Nayru",
            "score": 58721
          },
          {
            "rank": 2,
            "username": "Focus",
            "score": 55144
          },
          {
            "rank": 3,
            "username": "DesKismet",
            "score": 54366
          },
          {
            "rank": 4,
            "username": "Rstar",
            "score": 53919
          },
          {
            "rank": 5,
            "username": "Horseytink",
            "score": 53858
          },
          {
            "rank": 6,
            "username": "scortatia",
            "score": 53580
          },
          {
            "rank": 7,
            "username": "Fotogirl",
            "score": 53284
          },
          {
            "rank": 8,
            "username": "Myth",
            "score": 53175
          },
          {
            "rank": 9,
            "username": "aldisneyfans",
            "score": 53053
          },
          {
            "rank": 10,
            "username": "HappyToughFish",
            "score": 52449
          }
        ]
      }
    }
  }
}